nlpPandas
