Metadata-Version: 2.1
Name: nlpPandas
Version: 1.1.1
Summary: Easy NLP preprocessing for a Pandas dataframe
Home-page: https://github.com/brucewlee
Author: Bruce W. Lee
Author-email: phys.w.s.lee@gmail.com
License: cc-by-nc-sa-4.0
Keywords: NLP,Pandas,Preprocessing
Platform: UNKNOWN
Classifier: Development Status :: 5 - Production/Stable
Classifier: Intended Audience :: Developers
Classifier: Topic :: Software Development :: Build Tools
Classifier: Intended Audience :: Education
Classifier: Intended Audience :: Science/Research
Classifier: Programming Language :: Python :: 3.6
Classifier: Programming Language :: Python :: 3.7
Classifier: Programming Language :: Python :: 3.8
Classifier: Programming Language :: Python :: 3.9
License-File: license.txt
